matchkit/__init__.py
matchkit/core.py
matchkit-0.0.1.dist-info/LICENSE
matchkit-0.0.1.dist-info/METADATA
matchkit-0.0.1.dist-info/WHEEL
matchkit-0.0.1.dist-info/top_level.txt
matchkit-0.0.1.dist-info/RECORD
