Metadata-Version: 2.1
Name: matchkit
Version: 0.0.1
Summary: Test objects which pass equality checks with other objects.
Home-page: https://github.com/hypothesis/matchkit
Project-URL: Bug Tracker, https://github.com/hypothesis/matchkit/issues
Project-URL: Changelog, https://github.com/hypothesis/matchkit/releases
Classifier: Programming Language :: Python :: 3
Classifier: License :: OSI Approved :: BSD License
Classifier: Intended Audience :: Developers
Requires-Python: >=3.8
License-File: LICENSE
